logistics_notifier/__init__.py
logistics_notifier/audit.py
logistics_notifier/notification_handler.py
logistics_notifier/notification_manager.py
logistics_notifier/notifier.py
logistics_notifier/payloads.py
logistics_notifier/scheduler.py
logistics_notifier/templates.py
logistics_notifier-0.1.4.dist-info/METADATA
logistics_notifier-0.1.4.dist-info/WHEEL
logistics_notifier-0.1.4.dist-info/top_level.txt
logistics_notifier-0.1.4.dist-info/RECORD
