Metadata-Version: 2.1
Name: logistics-notifier
Version: 0.1.4
Summary: A library to send notifications for logistics.
Home-page: https://github.com/psunny25/logistics-notifier
Author: Paras Sunny
Author-email: your_email@example.com
Classifier: Programming Language :: Python :: 3
Classifier: License :: OSI Approved :: MIT License
Classifier: Operating System :: OS Independent
Requires-Python: >=3.6
Requires-Dist: schedule
